gps_data_codec-1.6.6.dist-info/METADATA
gps_data_codec-1.6.6.dist-info/WHEEL
gps_data_codec/__init__.py
gps_data_codec/gps_data_codec.cpython-313-x86_64-linux-gnu.so
gps_data_codec-1.6.6.dist-info/RECORD
