Metadata-Version: 2.4
Name: gps-data-codec
Version: 1.6.6
Keywords: gps,data,encode,decode
Home-Page: https://github.com/routechoices/gps-data-codec
Author: Raphael Stefanini <raphael@routechoices.com>
Author-email: Raphael Stefanini <raphael@routechoices.com>
License: MIT
Project-URL: Source Code, https://github.com/routechoices/gps-data-codec.git
